insightai/__init__.py
insightai/df_ontology.py
insightai/func_calls.py
insightai/gemini_models.py
insightai/groq_models.py
insightai/insightai.py
insightai/log_manager.py
insightai/models.py
insightai/openai_models.py
insightai/output_manager.py
insightai/prompts.py
insightai/reg_ex.py
insightai/utils.py
insightai-0.5.1.dist-info/METADATA
insightai-0.5.1.dist-info/WHEEL
insightai-0.5.1.dist-info/top_level.txt
insightai-0.5.1.dist-info/RECORD
