Metadata-Version: 2.4
Name: insightai
Version: 0.5.1
Summary: A lightweight library for dataset insights...
Author-email: Sohaib Ahmed <l215635@lhr.nu.edu.pk>
Project-URL: Homepage, https://github.com/LeoRigasaki/InSightAI
Project-URL: Repository, https://github.com/LeoRigasaki/InSightAI.git
Classifier: Development Status :: 3 - Alpha
Classifier: License :: OSI Approved :: MIT License
Classifier: Programming Language :: Python :: 3
Classifier: Programming Language :: Python :: 3.8
Classifier: Programming Language :: Python :: 3.9
Requires-Python: >=3.8
Requires-Dist: openai>=1.0.0
Requires-Dist: tiktoken>=0.5.0
Requires-Dist: pandas>=2.0.0
Requires-Dist: termcolor>=2.0.0
Requires-Dist: groq>=0.4.0
Requires-Dist: google-generativeai>=0.3.0
Requires-Dist: matplotlib>=3.5.0
Requires-Dist: seaborn>=0.11.0
Requires-Dist: scikit-learn>=1.0.0
Requires-Dist: ipython>=7.0.0
Requires-Dist: pyyaml>=6.0.0
